setup.py
test_vision.egg-info/PKG-INFO
test_vision.egg-info/SOURCES.txt
test_vision.egg-info/dependency_links.txt
test_vision.egg-info/pbr.json
test_vision.egg-info/requires.txt
test_vision.egg-info/top_level.txt
vision/__init__.py
vision/upload_to_s3.py
vision/upload_to_s3_exe.py